{
  "$schema": "https://raw.githubusercontent.com/googleapis/release-please/main/schemas/config.json",
  "always-update": true,
  "draft-pull-request": true,
  "separate-pull-requests": true,
  "include-component-in-tag": true,
  "include-v-in-tag": true,
  "release-type": "rust",
  "packages": {
    "post-compute": {
      "component": "post-compute",
      "package-name": "tee-worker-post-compute"
    },
    "pre-compute": {
      "component": "pre-compute",
      "package-name": "tee-worker-pre-compute"
    }
  },
  "changelog-path": "CHANGELOG.md",
  "changelog-sections": [
    {
      "type": "ci",
      "section": "🧰 Others",
      "hidden": false
    }
  ]
}
